halox/__init__.py
halox/bias.py
halox/cosmology.py
halox/hmf.py
halox/lss.py
halox/halo/__init__.py
halox/halo/nfw.py
halox-1.1.2.dist-info/METADATA
halox-1.1.2.dist-info/WHEEL
halox-1.1.2.dist-info/licenses/LICENSE
halox-1.1.2.dist-info/RECORD
